axiom/__init__.py
axiom/_fincache.py
axiom/_pysqlite2.py
axiom/_schema.py
axiom/_version.py
axiom/attributes.py
axiom/batch.py
axiom/batch.tac
axiom/dependency.py
axiom/errors.py
axiom/iaxiom.py
axiom/item.py
axiom/listversions.py
axiom/queryutil.py
axiom/scheduler.py
axiom/sequence.py
axiom/slotmachine.py
axiom/store.py
axiom/substore.py
axiom/tags.py
axiom/upgrade.py
axiom/userbase.py
axiom/benchmarks/benchmark_batchitemcreation.py
axiom/benchmarks/benchmark_batchitemdeletion.py
axiom/benchmarks/benchmark_itemcreation.py
axiom/benchmarks/benchmark_itemdeletion.py
axiom/benchmarks/benchmark_tagnames.py
axiom/benchmarks/benchmark_tagsof.py
axiom/benchmarks/testbase.py
axiom/benchmarks/testindex.py
axiom/benchmarks/testinit.py
axiom/benchmarks/testreader.py
axiom/benchmarks/testwriter.py
axiom/examples/bucket.py
axiom/examples/library.py
axiom/plugins/__init__.py
axiom/plugins/axiom_plugins.py
axiom/scripts/__init__.py
axiom/scripts/axiomatic.py
axiom/scripts/pysql.py
axiom/test/__init__.py
axiom/test/brokenapp.py
axiom/test/cursortest.py
axiom/test/deleteswordapp.py
axiom/test/itemtest.py
axiom/test/itemtestmain.py
axiom/test/morenewapp.py
axiom/test/newapp.py
axiom/test/newcirc.py
axiom/test/newobsolete.py
axiom/test/newpath.py
axiom/test/oldapp.py
axiom/test/oldcirc.py
axiom/test/oldobsolete.py
axiom/test/oldpath.py
axiom/test/onestepapp.py
axiom/test/openthenload.py
axiom/test/path_postcopy.py
axiom/test/reactorimporthelper.py
axiom/test/strategies.py
axiom/test/test_attributes.py
axiom/test/test_axiomatic.py
axiom/test/test_batch.py
axiom/test/test_count.py
axiom/test/test_crossstore.py
axiom/test/test_dependency.py
axiom/test/test_files.py
axiom/test/test_fincache.py
axiom/test/test_inheritance.py
axiom/test/test_item.py
axiom/test/test_listversions.py
axiom/test/test_mixin.py
axiom/test/test_paginate.py
axiom/test/test_powerup.py
axiom/test/test_pysqlite2.py
axiom/test/test_query.py
axiom/test/test_queryutil.py
axiom/test/test_reference.py
axiom-0.9.0.dist-info/LICENSE
axiom-0.9.0.dist-info/METADATA
axiom-0.9.0.dist-info/WHEEL
axiom-0.9.0.dist-info/top_level.txt
axiom-0.9.0.dist-info/RECORD
