Metadata-Version: 2.1
Name: axiom
Version: 0.9.0
Summary: An in-process object-relational database
Home-page: https://github.com/twisted/axiom
License: UNKNOWN
Platform: UNKNOWN
Classifier: Development Status :: 5 - Production/Stable
Classifier: Framework :: Twisted
Classifier: Intended Audience :: Developers
Classifier: License :: OSI Approved :: MIT License
Classifier: Programming Language :: Python
Classifier: Programming Language :: Python :: 2
Classifier: Programming Language :: Python :: 2.7
Classifier: Programming Language :: Python :: 2 :: Only
Classifier: Topic :: Database
Requires-Python: <3,>=2.7
Requires-Dist: argon2-cffi
Requires-Dist: epsilon (>=0.7.0)
Requires-Dist: twisted[tls] (>=13.2.0)
Requires-Dist: txpasslib
Provides-Extra: test
Requires-Dist: hypothesis[datetime] (<3.0.0,>=2.0.0) ; extra == 'test'
